bash.py
bash.py-0.4.2.dist-info/LICENSE
bash.py-0.4.2.dist-info/METADATA
bash.py-0.4.2.dist-info/WHEEL
bash.py-0.4.2.dist-info/top_level.txt
bash.py-0.4.2.dist-info/RECORD
